tle2czml/__init__.py
tle2czml/czml.py
tle2czml/rgba_list.txt
tle2czml/tle2czml.py
tle2czml-0.3.dist-info/LICENSE
tle2czml-0.3.dist-info/METADATA
tle2czml-0.3.dist-info/WHEEL
tle2czml-0.3.dist-info/top_level.txt
tle2czml-0.3.dist-info/RECORD
